jjuke_diffusion/__init__.py
jjuke_diffusion/diffusers080/__init__.py
jjuke_diffusion/diffusers080/load_hf_model.py
jjuke_diffusion/diffusers080/models/__init__.py
jjuke_diffusion/diffusers080/models/attention.py
jjuke_diffusion/diffusers080/models/embeddings.py
jjuke_diffusion/diffusers080/models/resnet.py
jjuke_diffusion/diffusers080/models/unet_2d_blocks.py
jjuke_diffusion/diffusers080/models/unet_2d_condition.py
jjuke_diffusion/diffusers080/utils/__init__.py
jjuke_diffusion/diffusers080/utils/import_utils.py
jjuke_diffusion/diffusers080/utils/modeling_utils.py
jjuke_diffusion/diffusers080/utils/outputs.py
jjuke_diffusion/diffusion/__init__.py
jjuke_diffusion/diffusion/common.py
jjuke_diffusion/diffusion/ddim.py
jjuke_diffusion/diffusion/ddpm.py
jjuke_diffusion/diffusion/diffusion_base.py
jjuke_diffusion/diffusion/gaussian_diffusion.py
jjuke_diffusion/diffusion/karras.py
jjuke_diffusion/diffusion/ldm.py
jjuke_diffusion/unet/__init__.py
jjuke_diffusion/unet/base_modules.py
jjuke_diffusion/unet/unet_base.py
jjuke_diffusion/unet/unet_modules.py
jjuke_diffusion/unet_cond/__init__.py
jjuke_diffusion/unet_cond/attention.py
jjuke_diffusion/unet_cond/fp16_util.py
jjuke_diffusion/unet_cond/transformer.py
jjuke_diffusion/unet_cond/unet.py
jjuke_diffusion/unet_cond/unet_modules.py
jjuke_diffusion-0.0.1.1.dist-info/METADATA
jjuke_diffusion-0.0.1.1.dist-info/WHEEL
jjuke_diffusion-0.0.1.1.dist-info/top_level.txt
jjuke_diffusion-0.0.1.1.dist-info/RECORD
