Metadata-Version: 2.1
Name: jjuke-diffusion
Version: 0.0.1.1
Summary: Use diffusions for various models
Home-page: https://github.com/JJukE/JJukE_Diffusion.git
Author: JJukE
Author-email: psj9156@gmail.com
Keywords: JJukE_Diffusion,JJukE-Diffusion,jjuke_diffusion,jjuke-diffusion
Classifier: Programming Language :: Python :: 3
Classifier: License :: OSI Approved :: MIT License
Classifier: Operating System :: OS Independent
Requires-Python: >=3
Requires-Dist: numpy
Requires-Dist: torch
Requires-Dist: einops
Requires-Dist: scipy
Requires-Dist: jjuke
